rustyrs-0.5.5.dist-info/METADATA
rustyrs-0.5.5.dist-info/WHEEL
rustyrs/__init__.py
rustyrs/__init__.pyi
rustyrs/py.typed
rustyrs/rustyrs.cpython-311-darwin.so
rustyrs-0.5.5.dist-info/RECORD
