Metadata-Version: 2.4
Name: rustyrs
Version: 0.5.5
Summary: Generates unique slugs for various uses
Keywords: random,slug,python,wasm
Author: nicelgueta
License: MIT
Project-URL: Source Code, https://github.com/nicelgueta/rusty-random-slug
